LICENSE
MANIFEST.in
README.md
setup.cfg
setup.py
src/tenzing/__init__.py
src/tenzing.egg-info/PKG-INFO
src/tenzing.egg-info/SOURCES.txt
src/tenzing.egg-info/dependency_links.txt
src/tenzing.egg-info/requires.txt
src/tenzing.egg-info/top_level.txt
src/tenzing/core/__init__.py
src/tenzing/core/mixins.py
src/tenzing/core/models.py
src/tenzing/core/plotting.py
src/tenzing/core/summary.py
src/tenzing/core/typesets.py
src/tenzing/core/model_implementations/__init__.py
src/tenzing/core/model_implementations/types.py
src/tenzing/core/model_implementations/typesets.py
src/tenzing/templates/base.html
src/tenzing/templates/column_overview.html
src/tenzing/templates/frequency_table.html
src/tenzing/templates/html_wrapper.html
src/tenzing/templates/list_composition.html
src/tenzing/templates/overview.html
src/tenzing/utils/__init__.py
src/tenzing/utils/singleton.py
src/tenzing/utils/test_utils.py