Metadata-Version: 2.1
Name: tenzing
Version: 0.0.2
Summary: Tenzing
Home-page: UNKNOWN
License: UNKNOWN
Platform: UNKNOWN
Requires-Python: >=3.4
Provides-Extra: shapely
Provides-Extra: geopandas
